AUTHORS.rst
CONTRIBUTING.rst
HISTORY.rst
LICENSE
MANIFEST.in
README.rst
setup.cfg
setup.py
molecules/__init__.py
molecules.egg-info/PKG-INFO
molecules.egg-info/SOURCES.txt
molecules.egg-info/dependency_links.txt
molecules.egg-info/not-zip-safe
molecules.egg-info/requires.txt
molecules.egg-info/top_level.txt
molecules/data/__init__.py
molecules/data/dataloaders/__init__.py
molecules/data/dataloaders/dataset.py
molecules/ml/__init__.py
molecules/ml/rl/__init__.py
molecules/ml/rl/reinforce.py
molecules/ml/rl/models/__init__.py
molecules/ml/rl/models/fc_policy.py
molecules/ml/supervised/__init__.py
molecules/ml/unsupervised/__init__.py
molecules/ml/unsupervised/callbacks.py
molecules/ml/unsupervised/vae.py
molecules/ml/unsupervised/conv_vae/__init__.py
molecules/ml/unsupervised/conv_vae/decoder.py
molecules/ml/unsupervised/conv_vae/encoder.py
molecules/sim/__init__.py
molecules/sim/md_analysis/__init__.py
molecules/sim/md_analysis/contact_maps.py
molecules/sim/md_simulation/__init__.py
molecules/sim/md_simulation/openmm_simulation.py
test/__init__.py
test/test_molecules.py