Metadata-Version: 1.1
Name: molecules
Version: 0.0.3.2
Summary: Machine learning for molecular dynamics.
Home-page: https://github.com/yngtodd/molecules
Author: Todd Young
Author-email: youngmt1@ornl.gov
License: MIT
Keywords: molecules
Platform: UNKNOWN
Classifier: Development Status :: 2 - Pre-Alpha
Classifier: Intended Audience :: Developers
Classifier: License :: OSI Approved :: MIT License
Classifier: Natural Language :: English
Classifier: Programming Language :: Python :: 3.6
Classifier: Programming Language :: Python :: Implementation :: PyPy
